sabapipeline/__init__.py
sabapipeline/__private/__init__.py
sabapipeline/__private/bus.py
sabapipeline/__private/concepts.py
sabapipeline/__private/elements.py
sabapipeline/__private/modlue.py
sabapipeline/__private/utilities.py
sabapipeline/kafka/__init__.py
sabapipeline/kafka/__private/__init__.py
sabapipeline/kafka/__private/data_types.py
sabapipeline/kafka/__private/pipeline_elements.py
saba_pipeline-0.0.1.dist-info/LICENSE
saba_pipeline-0.0.1.dist-info/METADATA
saba_pipeline-0.0.1.dist-info/WHEEL
saba_pipeline-0.0.1.dist-info/top_level.txt
saba_pipeline-0.0.1.dist-info/RECORD
