Metadata-Version: 2.1
Name: saba-pipeline
Version: 0.0.1
Summary: A package for running data pipelines. It contains various types of source and sinks and handles many side operations
Home-page: https://github.com/pypa/sampleproject
Author: Ali Taheri
Author-email: ataheri@ce.sharif.edu
License: UNKNOWN
Project-URL: Bug Tracker, https://github.com/pypa/sampleproject/issues
Platform: UNKNOWN
Classifier: Programming Language :: Python :: 3
Classifier: License :: OSI Approved :: MIT License
Classifier: Operating System :: OS Independent
Requires-Python: >=3.7
License-File: LICENSE
